{
    "../../PunkBot": {
        "name": "PunkBot",
        "path": "../../PunkBot",
        "type": "Folder",
        "folder": "../..",
        "category": "Poses",
        "modified": 1746165084.3174863,
        "__class__": "studiolibrary.folderitem.FolderItem"
    },
    "../../PunkBot/Body": {
        "name": "Body",
        "path": "../../PunkBot/Body",
        "type": "Folder",
        "folder": "../../PunkBot",
        "category": "PunkBot",
        "modified": 1746165154.931504,
        "__class__": "studiolibrary.folderitem.FolderItem"
    },
    "../../PunkBot/Body/TPoseHandsDown.pose": {
        "name": "TPoseHandsDown.pose",
        "path": "../../PunkBot/Body/TPoseHandsDown.pose",
        "type": ".pose",
        "folder": "../../PunkBot/Body",
        "category": "Body",
        "modified": 1747824184.3191385,
        "__class__": "studiolibrarymaya.poseitem.PoseItem"
    },
    "../../PunkBot/Hands": {
        "name": "Hands",
        "path": "../../PunkBot/Hands",
        "type": "Folder",
        "folder": "../../PunkBot",
        "category": "PunkBot",
        "modified": 1746165175.45326,
        "__class__": "studiolibrary.folderitem.FolderItem"
    },
    "../../PunkBot/Hands/Grab.pose": {
        "name": "Grab.pose",
        "path": "../../PunkBot/Hands/Grab.pose",
        "type": ".pose",
        "folder": "../../PunkBot/Hands",
        "category": "Hands",
        "modified": 1747733266.1823626,
        "__class__": "studiolibrarymaya.poseitem.PoseItem"
    },
    "../../PunkBot/Hands/GrabPipe.pose": {
        "name": "GrabPipe.pose",
        "path": "../../PunkBot/Hands/GrabPipe.pose",
        "type": ".pose",
        "folder": "../../PunkBot/Hands",
        "category": "Hands",
        "modified": 1747826165.4957268,
        "__class__": "studiolibrarymaya.poseitem.PoseItem"
    },
    "../../PunkBot/Hands/GrabPipeLeft.pose": {
        "name": "GrabPipeLeft.pose",
        "path": "../../PunkBot/Hands/GrabPipeLeft.pose",
        "type": ".pose",
        "folder": "../../PunkBot/Hands",
        "category": "Hands",
        "modified": 1747918012.0143805,
        "__class__": "studiolibrarymaya.poseitem.PoseItem"
    },
    "../../PunkBot/Hands/SKPipeJointRdyWalks.pose": {
        "name": "SKPipeJointRdyWalks.pose",
        "path": "../../PunkBot/Hands/SKPipeJointRdyWalks.pose",
        "type": ".pose",
        "folder": "../../PunkBot/Hands",
        "category": "Hands",
        "modified": 1747745337.6927454,
        "__class__": "studiolibrarymaya.poseitem.PoseItem"
    },
    "../../PunkBot/Hands/SkGrab.pose": {
        "name": "SkGrab.pose",
        "path": "../../PunkBot/Hands/SkGrab.pose",
        "type": ".pose",
        "folder": "../../PunkBot/Hands",
        "category": "Hands",
        "modified": 1747740772.232461,
        "__class__": "studiolibrarymaya.poseitem.PoseItem"
    },
    "../../PunkBot/Hands/SkTightSlight.pose": {
        "name": "SkTightSlight.pose",
        "path": "../../PunkBot/Hands/SkTightSlight.pose",
        "type": ".pose",
        "folder": "../../PunkBot/Hands",
        "category": "Hands",
        "modified": 1747743572.3438132,
        "__class__": "studiolibrarymaya.poseitem.PoseItem"
    },
    "../../PunkBot/MirrorTable.mirror": {
        "name": "MirrorTable.mirror",
        "path": "../../PunkBot/MirrorTable.mirror",
        "type": ".mirror",
        "folder": "../../PunkBot",
        "category": "PunkBot",
        "modified": 1747296036.0067563,
        "__class__": "studiolibrarymaya.mirroritem.MirrorItem"
    },
    "../../PunkBot/RoboticaB": {
        "name": "RoboticaB",
        "path": "../../PunkBot/RoboticaB",
        "type": "Folder",
        "folder": "../../PunkBot",
        "category": "PunkBot",
        "modified": 1747298763.863274,
        "__class__": "studiolibrary.folderitem.FolderItem"
    },
    "../../PunkBot/RoboticaB/Idle.pose": {
        "name": "Idle.pose",
        "path": "../../PunkBot/RoboticaB/Idle.pose",
        "type": ".pose",
        "folder": "../../PunkBot/RoboticaB",
        "category": "RoboticaB",
        "modified": 1747733486.9406962,
        "__class__": "studiolibrarymaya.poseitem.PoseItem"
    },
    "../../PunkBot/RoboticaB/IdleRdy.pose": {
        "name": "IdleRdy.pose",
        "path": "../../PunkBot/RoboticaB/IdleRdy.pose",
        "type": ".pose",
        "folder": "../../PunkBot/RoboticaB",
        "category": "RoboticaB",
        "modified": 1747732980.8697581,
        "__class__": "studiolibrarymaya.poseitem.PoseItem"
    },
    "../../PunkBot/RoboticaB/SKIdle.pose": {
        "name": "SKIdle.pose",
        "path": "../../PunkBot/RoboticaB/SKIdle.pose",
        "type": ".pose",
        "folder": "../../PunkBot/RoboticaB",
        "category": "RoboticaB",
        "modified": 1747734278.4562852,
        "__class__": "studiolibrarymaya.poseitem.PoseItem"
    },
    "../../PunkBot/RoboticaB/SKIdleRdy.pose": {
        "name": "SKIdleRdy.pose",
        "path": "../../PunkBot/RoboticaB/SKIdleRdy.pose",
        "type": ".pose",
        "folder": "../../PunkBot/RoboticaB",
        "category": "RoboticaB",
        "modified": 1747734248.1836503,
        "__class__": "studiolibrarymaya.poseitem.PoseItem"
    },
    "../../PunkBot/Skeleton": {
        "name": "Skeleton",
        "path": "../../PunkBot/Skeleton",
        "type": "Folder",
        "folder": "../../PunkBot",
        "category": "PunkBot",
        "modified": 1746165093.7091403,
        "__class__": "studiolibrary.folderitem.FolderItem"
    },
    "../../PunkBot/Skeleton/APose-Broad.pose": {
        "name": "APose-Broad.pose",
        "path": "../../PunkBot/Skeleton/APose-Broad.pose",
        "type": ".pose",
        "folder": "../../PunkBot/Skeleton",
        "category": "Skeleton",
        "modified": 1746601740.3835123,
        "__class__": "studiolibrarymaya.poseitem.PoseItem"
    },
    "../../PunkBot/Skeleton/APose-Tight.pose": {
        "name": "APose-Tight.pose",
        "path": "../../PunkBot/Skeleton/APose-Tight.pose",
        "type": ".pose",
        "folder": "../../PunkBot/Skeleton",
        "category": "Skeleton",
        "modified": 1746166284.200783,
        "__class__": "studiolibrarymaya.poseitem.PoseItem"
    },
    "../../PunkBot/Skeleton/HandsAPose-Tight.pose": {
        "name": "HandsAPose-Tight.pose",
        "path": "../../PunkBot/Skeleton/HandsAPose-Tight.pose",
        "type": ".pose",
        "folder": "../../PunkBot/Skeleton",
        "category": "Skeleton",
        "modified": 1746166446.8006237,
        "__class__": "studiolibrarymaya.poseitem.PoseItem"
    },
    "../../PunkBot/Skeleton/SK_TPose.pose": {
        "name": "SK_TPose.pose",
        "path": "../../PunkBot/Skeleton/SK_TPose.pose",
        "type": ".pose",
        "folder": "../../PunkBot/Skeleton",
        "category": "Skeleton",
        "modified": 1748256483.5126595,
        "__class__": "studiolibrarymaya.poseitem.PoseItem"
    },
    "../../PunkBot/Skeleton/TPose-All.pose": {
        "name": "TPose-All.pose",
        "path": "../../PunkBot/Skeleton/TPose-All.pose",
        "type": ".pose",
        "folder": "../../PunkBot/Skeleton",
        "category": "PunkBot",
        "modified": 1746163896.215367,
        "__class__": "studiolibrarymaya.poseitem.PoseItem"
    },
    "../../PunkBot/Skeleton/TPose-Controls.pose": {
        "name": "TPose-Controls.pose",
        "path": "../../PunkBot/Skeleton/TPose-Controls.pose",
        "type": ".pose",
        "folder": "../../PunkBot/Skeleton",
        "category": "PunkBot",
        "modified": 1746164052.6678412,
        "__class__": "studiolibrarymaya.poseitem.PoseItem"
    },
    "../../PunkBot/Skeleton/TPose-Everything.pose": {
        "name": "TPose-Everything.pose",
        "path": "../../PunkBot/Skeleton/TPose-Everything.pose",
        "type": ".pose",
        "folder": "../../PunkBot/Skeleton",
        "category": "PunkBot",
        "modified": 1746164117.763531,
        "__class__": "studiolibrarymaya.poseitem.PoseItem"
    },
    "../../PunkBot/Skeleton/TPose-Hip.pose": {
        "name": "TPose-Hip.pose",
        "path": "../../PunkBot/Skeleton/TPose-Hip.pose",
        "type": ".pose",
        "folder": "../../PunkBot/Skeleton",
        "category": "PunkBot",
        "modified": 1746163934.0566554,
        "__class__": "studiolibrarymaya.poseitem.PoseItem"
    },
    "../../PunkBot/Skeleton/TPose-beforeRig.pose": {
        "name": "TPose-beforeRig.pose",
        "path": "../../PunkBot/Skeleton/TPose-beforeRig.pose",
        "type": ".pose",
        "folder": "../../PunkBot/Skeleton",
        "category": "Skeleton",
        "modified": 1746690289.9733386,
        "__class__": "studiolibrarymaya.poseitem.PoseItem"
    },
    "../../Trash/APose-Broad.pose": {
        "name": "APose-Broad.pose",
        "path": "../../Trash/APose-Broad.pose",
        "type": ".pose",
        "folder": "../../Trash",
        "category": "Trash",
        "modified": 1746597524.0452423,
        "__class__": "studiolibrary.libraryitem.LibraryItem"
    },
    "../../Trash/Grab (2).pose": {
        "name": "Grab (2).pose",
        "path": "../../Trash/Grab (2).pose",
        "type": ".pose",
        "folder": "../../Trash",
        "category": "Trash",
        "modified": 1747383084.7549236,
        "__class__": "studiolibrary.libraryitem.LibraryItem"
    },
    "../../Trash/Grab.pose": {
        "name": "Grab.pose",
        "path": "../../Trash/Grab.pose",
        "type": ".pose",
        "folder": "../../Trash",
        "category": "Trash",
        "modified": 1747297541.0046496,
        "__class__": "studiolibrary.libraryitem.LibraryItem"
    },
    "../../Trash/GrabControls (2).pose": {
        "name": "GrabControls (2).pose",
        "path": "../../Trash/GrabControls (2).pose",
        "type": ".pose",
        "folder": "../../Trash",
        "category": "Trash",
        "modified": 1747295342.963857,
        "__class__": "studiolibrary.libraryitem.LibraryItem"
    },
    "../../Trash/GrabControls (3).pose": {
        "name": "GrabControls (3).pose",
        "path": "../../Trash/GrabControls (3).pose",
        "type": ".pose",
        "folder": "../../Trash",
        "category": "Trash",
        "modified": 1747296228.5571551,
        "__class__": "studiolibrary.libraryitem.LibraryItem"
    },
    "../../Trash/GrabControls (4).pose": {
        "name": "GrabControls (4).pose",
        "path": "../../Trash/GrabControls (4).pose",
        "type": ".pose",
        "folder": "../../Trash",
        "category": "Trash",
        "modified": 1747296415.177119,
        "__class__": "studiolibrarymaya.poseitem.PoseItem"
    },
    "../../Trash/GrabControls.pose": {
        "name": "GrabControls.pose",
        "path": "../../Trash/GrabControls.pose",
        "type": ".pose",
        "folder": "../../Trash",
        "category": "Trash",
        "modified": 1747296211.5138485,
        "__class__": "studiolibrarymaya.poseitem.PoseItem"
    },
    "../../Trash/GrabPipe.pose": {
        "name": "GrabPipe.pose",
        "path": "../../Trash/GrabPipe.pose",
        "type": ".pose",
        "folder": "../../Trash",
        "category": "Trash",
        "modified": 1747826056.7789955,
        "__class__": "studiolibrary.libraryitem.LibraryItem"
    },
    "../../Trash/Idle (2).pose": {
        "name": "Idle (2).pose",
        "path": "../../Trash/Idle (2).pose",
        "type": ".pose",
        "folder": "../../Trash",
        "category": "Trash",
        "modified": 1747733436.323735,
        "__class__": "studiolibrary.libraryitem.LibraryItem"
    },
    "../../Trash/Idle.pose": {
        "name": "Idle.pose",
        "path": "../../Trash/Idle.pose",
        "type": ".pose",
        "folder": "../../Trash",
        "category": "Trash",
        "modified": 1747733216.2578008,
        "__class__": "studiolibrary.libraryitem.LibraryItem"
    },
    "../../Trash/IdleRdy.pose": {
        "name": "IdleRdy.pose",
        "path": "../../Trash/IdleRdy.pose",
        "type": ".pose",
        "folder": "../../Trash",
        "category": "Trash",
        "modified": 1747383084.7659862,
        "__class__": "studiolibrary.libraryitem.LibraryItem"
    },
    "../../Trash/MirrorTable.mirror": {
        "name": "MirrorTable.mirror",
        "path": "../../Trash/MirrorTable.mirror",
        "type": ".mirror",
        "folder": "../../Trash",
        "category": "Trash",
        "modified": 1747295853.8683238,
        "__class__": "studiolibrarymaya.mirroritem.MirrorItem"
    },
    "../../Trash/PunkBotBody": {
        "name": "PunkBotBody",
        "path": "../../Trash/PunkBotBody",
        "type": "Folder",
        "folder": "../../Trash",
        "category": "Trash",
        "modified": 1746165064.6647842,
        "__class__": "studiolibrary.folderitem.FolderItem"
    },
    "../../Trash/Robotica.mirror": {
        "name": "Robotica.mirror",
        "path": "../../Trash/Robotica.mirror",
        "type": ".mirror",
        "folder": "../../Trash",
        "category": "Trash",
        "modified": 1747295995.1430566,
        "__class__": "studiolibrarymaya.mirroritem.MirrorItem"
    },
    "../../Trash/Test.set": {
        "name": "Test.set",
        "path": "../../Trash/Test.set",
        "type": ".set",
        "folder": "../../Trash",
        "category": "Trash",
        "modified": 1747297720.6916196,
        "__class__": "studiolibrarymaya.setsitem.SetsItem"
    },
    "../../Trash/hand.pose": {
        "name": "hand.pose",
        "path": "../../Trash/hand.pose",
        "type": ".pose",
        "folder": "../../Trash",
        "category": "Trash",
        "modified": 1748004724.869127,
        "__class__": "studiolibrarymaya.poseitem.PoseItem"
    }
}